py_gen_server/__init__.py
py_gen_server/actor.py
py_gen_server/actor_doc.md
py_gen_server/py.typed
py_gen_server-0.0.0.dist-info/WHEEL
py_gen_server-0.0.0.dist-info/METADATA
py_gen_server-0.0.0.dist-info/RECORD
