Metadata-Version: 2.3
Name: py_gen_server
Version: 0.0.0
Summary: Erlang-style generic server (GenServer) actors
Author: Steven Hé (Sīchàng)
Author-email: Steven Hé (Sīchàng) <stevensichanghe@gmail.com>
Requires-Dist: aio-sync>=0.2.0
Requires-Python: >=3.13
